MANIFEST.in
README.md
requirements.txt
setup.cfg
setup.py
bin/noderegister
noderegister/__init__.py
noderegister/register.py
noderegister.egg-info/PKG-INFO
noderegister.egg-info/SOURCES.txt
noderegister.egg-info/dependency_links.txt
noderegister.egg-info/requires.txt
noderegister.egg-info/top_level.txt