Metadata-Version: 2.1
Name: noderegister
Version: 0.1.5
Summary: A Simple tool that registers ec2 host information to a DynamoDB Table
Home-page: https://avattathil.github.io/noderegister
Author: Tony Vattathil
Author-email: avattathil@gmail.com
License: Apache License 2.0
Download-URL: https://github.com/avattathil/noderegister/tarball/master
Keywords: aws,noderegister
Platform: UNKNOWN
Classifier: Development Status :: 4 - Beta
Classifier: Intended Audience :: Developers
Classifier: License :: OSI Approved :: Apache Software License
Classifier: Programming Language :: Python :: 3.5
Classifier: Programming Language :: Python :: 3.6
Classifier: Programming Language :: Python :: 3.7
Classifier: Topic :: Software Development :: Libraries
Classifier: Operating System :: POSIX :: Linux
